odoo9_addon_crm_deduplicate_by_website-9.0.1.0.0-py2.7-nspkg.pth
odoo_addons/crm_deduplicate_by_website/__openerp__.py
odoo_addons/crm_deduplicate_by_website/__init__.py
odoo_addons/crm_deduplicate_by_website/README.rst
odoo_addons/crm_deduplicate_by_website/i18n/ja.po
odoo_addons/crm_deduplicate_by_website/i18n/lv.po
odoo_addons/crm_deduplicate_by_website/i18n/zh_CN.po
odoo_addons/crm_deduplicate_by_website/i18n/uk.po
odoo_addons/crm_deduplicate_by_website/i18n/es_AR.po
odoo_addons/crm_deduplicate_by_website/i18n/ko.po
odoo_addons/crm_deduplicate_by_website/i18n/ru.po
odoo_addons/crm_deduplicate_by_website/i18n/it.po
odoo_addons/crm_deduplicate_by_website/i18n/es_CL.po
odoo_addons/crm_deduplicate_by_website/i18n/es.po
odoo_addons/crm_deduplicate_by_website/i18n/ar.po
odoo_addons/crm_deduplicate_by_website/i18n/lt.po
odoo_addons/crm_deduplicate_by_website/i18n/sr.po
odoo_addons/crm_deduplicate_by_website/i18n/mk.po
odoo_addons/crm_deduplicate_by_website/i18n/hr.po
odoo_addons/crm_deduplicate_by_website/i18n/bg.po
odoo_addons/crm_deduplicate_by_website/i18n/es_EC.po
odoo_addons/crm_deduplicate_by_website/i18n/zh_TW.po
odoo_addons/crm_deduplicate_by_website/i18n/hu.po
odoo_addons/crm_deduplicate_by_website/i18n/ca.po
odoo_addons/crm_deduplicate_by_website/i18n/id.po
odoo_addons/crm_deduplicate_by_website/i18n/es_CR.po
odoo_addons/crm_deduplicate_by_website/i18n/he.po
odoo_addons/crm_deduplicate_by_website/i18n/es_CO.po
odoo_addons/crm_deduplicate_by_website/i18n/sl.po
odoo_addons/crm_deduplicate_by_website/i18n/sr@latin.po
odoo_addons/crm_deduplicate_by_website/i18n/th.po
odoo_addons/crm_deduplicate_by_website/i18n/es_PE.po
odoo_addons/crm_deduplicate_by_website/i18n/cs.po
odoo_addons/crm_deduplicate_by_website/i18n/nb.po
odoo_addons/crm_deduplicate_by_website/i18n/da.po
odoo_addons/crm_deduplicate_by_website/i18n/et.po
odoo_addons/crm_deduplicate_by_website/i18n/mn.po
odoo_addons/crm_deduplicate_by_website/i18n/de.po
odoo9_addon_crm_deduplicate_by_website-9.0.1.0.0.dist-info/top_level.txt
odoo9_addon_crm_deduplicate_by_website-9.0.1.0.0.dist-info/WHEEL
odoo9_addon_crm_deduplicate_by_website-9.0.1.0.0.dist-info/RECORD
odoo9_addon_crm_deduplicate_by_website-9.0.1.0.0.dist-info/metadata.json
odoo9_addon_crm_deduplicate_by_website-9.0.1.0.0.dist-info/DESCRIPTION.rst
odoo9_addon_crm_deduplicate_by_website-9.0.1.0.0.dist-info/METADATA
odoo9_addon_crm_deduplicate_by_website-9.0.1.0.0.dist-info/namespace_packages.txt
